{
  "unversionedId": "technicals-messaging",
  "id": "version-0.91.0/technicals-messaging",
  "title": "Messaging",
  "description": "tbd",
  "source": "@site/versioned_docs/version-0.91.0/07_technicals-messaging.md",
  "sourceDirName": ".",
  "slug": "/technicals-messaging",
  "permalink": "/docs/0.91.0/technicals-messaging",
  "draft": false,
  "tags": [],
  "version": "0.91.0",
  "lastUpdatedBy": "Author",
  "lastUpdatedAt": 1539502055,
  "formattedLastUpdatedAt": "Oct 14, 2018",
  "sidebarPosition": 7,
  "frontMatter": {
    "id": "technicals-messaging",
    "title": "Messaging",
    "sidebar_label": "Messaging",
    "original_id": "technicals-messaging"
  },
  "sidebar": "documentation",
  "previous": {
    "title": "Runtime Wrappers",
    "permalink": "/docs/0.91.0/technicals-runtime-wrappers"
  },
  "next": {
    "title": "Configuration",
    "permalink": "/docs/0.91.0/technicals-configuration"
  }
}