{
  "unversionedId": "extend-first-processor",
  "id": "version-0.92.0/extend-first-processor",
  "title": "Your first data processor",
  "description": "In this section, we will explain how to start a pipeline element service and install it using the StreamPipes UI.",
  "source": "@site/versioned_docs/version-0.92.0/06_extend-first-processor.md",
  "sourceDirName": ".",
  "slug": "/extend-first-processor",
  "permalink": "/docs/extend-first-processor",
  "draft": false,
  "tags": [],
  "version": "0.92.0",
  "lastUpdatedBy": "Author",
  "lastUpdatedAt": 1539502055,
  "formattedLastUpdatedAt": "Oct 14, 2018",
  "sidebarPosition": 6,
  "frontMatter": {
    "id": "extend-first-processor",
    "title": "Your first data processor",
    "sidebar_label": "Your first data processor"
  },
  "sidebar": "documentation",
  "previous": {
    "title": "Maven Archetypes",
    "permalink": "/docs/extend-archetypes"
  },
  "next": {
    "title": "Tutorial: Data Sources",
    "permalink": "/docs/extend-tutorial-data-sources"
  }
}