{
  "unversionedId": "pe/org.apache.streampipes.processors.aggregation.flink.count",
  "id": "pe/org.apache.streampipes.processors.aggregation.flink.count",
  "title": "Count Aggregation",
  "description": "<!--",
  "source": "@site/../docs/pe/org.apache.streampipes.processors.aggregation.flink.count.md",
  "sourceDirName": "pe",
  "slug": "/pe/org.apache.streampipes.processors.aggregation.flink.count",
  "permalink": "/docs/next/pe/org.apache.streampipes.processors.aggregation.flink.count",
  "draft": false,
  "tags": [],
  "version": "current",
  "lastUpdatedBy": "Author",
  "lastUpdatedAt": 1539502055,
  "formattedLastUpdatedAt": "Oct 14, 2018",
  "frontMatter": {
    "id": "org.apache.streampipes.processors.aggregation.flink.count",
    "title": "Count Aggregation",
    "sidebar_label": "Count Aggregation"
  },
  "sidebar": "documentation",
  "previous": {
    "title": "Compose",
    "permalink": "/docs/next/pe/org.apache.streampipes.processors.filters.jvm.compose"
  },
  "next": {
    "title": "Count Array",
    "permalink": "/docs/next/pe/org.apache.streampipes.processors.transformation.jvm.count-array"
  }
}