{
  "unversionedId": "pe/org.apache.streampipes.processors.enricher.flink.processor.trigonometry",
  "id": "version-0.70.0/pe/org.apache.streampipes.processors.enricher.flink.processor.trigonometry",
  "title": "Trigonometry Functions",
  "description": "<!--",
  "source": "@site/versioned_docs/version-0.70.0/pe/org.apache.streampipes.processors.enricher.flink.processor.trigonometry.md",
  "sourceDirName": "pe",
  "slug": "/pe/org.apache.streampipes.processors.enricher.flink.processor.trigonometry",
  "permalink": "/docs/0.70.0/pe/org.apache.streampipes.processors.enricher.flink.processor.trigonometry",
  "draft": false,
  "tags": [],
  "version": "0.70.0",
  "lastUpdatedBy": "Author",
  "lastUpdatedAt": 1539502055,
  "formattedLastUpdatedAt": "Oct 14, 2018",
  "frontMatter": {
    "id": "org.apache.streampipes.processors.enricher.flink.processor.trigonometry",
    "title": "Trigonometry Functions",
    "sidebar_label": "Trigonometry Functions",
    "original_id": "org.apache.streampipes.processors.enricher.flink.processor.trigonometry"
  },
  "sidebar": "documentation",
  "previous": {
    "title": "Trend",
    "permalink": "/docs/0.70.0/pe/org.apache.streampipes.processors.siddhi.increase"
  },
  "next": {
    "title": "URL Dereferencing",
    "permalink": "/docs/0.70.0/pe/org.apache.streampipes.processors.enricher.flink.processor.urldereferencing"
  }
}